appinfra/__init__.py
appinfra/_build_info.py
appinfra/deprecation.py
appinfra/dict.py
appinfra/dot_dict.py
appinfra/ewma.py
appinfra/exceptions.py
appinfra/py.typed
appinfra/rate_limit.py
appinfra/regex_utils.py
appinfra/size.py
appinfra/utils.py
appinfra/yaml.py
appinfra/app/__init__.py
appinfra/app/args.py
appinfra/app/constants.py
appinfra/app/decorators.py
appinfra/app/decorators.pyi
appinfra/app/errors.py
appinfra/app/testing.py
appinfra/app/utils.py
appinfra/app/builder/__init__.py
appinfra/app/builder/app.py
appinfra/app/builder/config.py
appinfra/app/builder/hook.py
appinfra/app/builder/middleware.py
appinfra/app/builder/plugin.py
appinfra/app/builder/tool.py
appinfra/app/builder/validation.py
appinfra/app/builder/configurer/__init__.py
appinfra/app/builder/configurer/advanced.py
appinfra/app/builder/configurer/logging.py
appinfra/app/builder/configurer/server.py
appinfra/app/builder/configurer/tool.py
appinfra/app/builder/configurer/version.py
appinfra/app/cli/__init__.py
appinfra/app/cli/commands.py
appinfra/app/cli/help.py
appinfra/app/cli/parser.py
appinfra/app/core/__init__.py
appinfra/app/core/app.py
appinfra/app/core/config.py
appinfra/app/core/lifecycle.py
appinfra/app/core/logging_utils.py
appinfra/app/core/shutdown.py
appinfra/app/docs/__init__.py
appinfra/app/docs/generator.py
appinfra/app/fastapi/__init__.py
appinfra/app/fastapi/plugin.py
appinfra/app/fastapi/builder/__init__.py
appinfra/app/fastapi/builder/route.py
appinfra/app/fastapi/builder/server.py
appinfra/app/fastapi/builder/subprocess.py
appinfra/app/fastapi/builder/uvicorn.py
appinfra/app/fastapi/config/__init__.py
appinfra/app/fastapi/config/api.py
appinfra/app/fastapi/config/ipc.py
appinfra/app/fastapi/config/uvicorn.py
appinfra/app/fastapi/runtime/__init__.py
appinfra/app/fastapi/runtime/adapter.py
appinfra/app/fastapi/runtime/ipc.py
appinfra/app/fastapi/runtime/logging.py
appinfra/app/fastapi/runtime/server.py
appinfra/app/fastapi/runtime/subprocess.py
appinfra-0.3.3.dist-info/licenses/LICENSE
appinfra-0.3.3.dist-info/METADATA
appinfra-0.3.3.dist-info/WHEEL
appinfra-0.3.3.dist-info/entry_points.txt
appinfra-0.3.3.dist-info/top_level.txt
appinfra-0.3.3.dist-info/RECORD
